[
  {
    "id" : 4,
    "product" : "젠틀 나잇 핸드 크림, 100ml",
    "note" : "무화과 | 화이트 티 | 스웨이드 | 시더우드",
    "price" : "38,000원"
  },
  {
    "id" : 5,
    "product" : "가이악 플라워 핸드 크림, 100ml",
    "note" : "와일드 로즈 | 가이악우드 | 앰버 | 바닐라",
    "price" : "38,000원"
  },
  {
    "id" : 6,
    "product" : "가이악 플라워 핸드 크림, 50ml",
    "note" : "와일드 로즈 | 가이악우드 | 앰버 | 바닐라",
    "price" : "25,000원"
  },
  {
    "id" : 7,
    "product" : "젠틀 나잇 핸드 크림, 50ml",
    "note" : "무화과 | 화이트 티 | 스웨이드 | 시더우드",
    "price" : "25,000원"
  }

]